pori_cbioportal/__init__.py
pori_cbioportal/expression.py
pori_cbioportal/main.py
pori_cbioportal/study.py
pori_cbioportal/util.py
tests/__init__.py
pori_cbioportal-0.1.1.dist-info/LICENSE
pori_cbioportal-0.1.1.dist-info/METADATA
pori_cbioportal-0.1.1.dist-info/WHEEL
pori_cbioportal-0.1.1.dist-info/entry_points.txt
pori_cbioportal-0.1.1.dist-info/top_level.txt
pori_cbioportal-0.1.1.dist-info/RECORD
