Metadata-Version: 2.1
Name: pori-cbioportal
Version: 0.1.1
Summary: UNKNOWN
Home-page: UNKNOWN
Author: creisle
Author-email: creisle@bcgsc.ca
Maintainer: creisle
Maintainer-email: creisle@bcgsc.ca
License: UNKNOWN
Platform: UNKNOWN
Requires-Python: >=3
License-File: LICENSE
Requires-Dist: ipr (<4.0.0,>=3.0.0)
Requires-Dist: pandas
Requires-Dist: graphkb
Requires-Dist: matplotlib
Requires-Dist: seaborn
Provides-Extra: deploy
Requires-Dist: twine ; extra == 'deploy'
Requires-Dist: wheel ; extra == 'deploy'
Requires-Dist: m2r ; extra == 'deploy'
Provides-Extra: dev
Requires-Dist: pytest ; extra == 'dev'
Requires-Dist: pytest-cov ; extra == 'dev'
Requires-Dist: twine ; extra == 'dev'
Requires-Dist: wheel ; extra == 'dev'
Requires-Dist: m2r ; extra == 'dev'
Requires-Dist: flake8 ; extra == 'dev'
Requires-Dist: black ; extra == 'dev'
Requires-Dist: mypy ; extra == 'dev'
Provides-Extra: test
Requires-Dist: pytest ; extra == 'test'
Requires-Dist: pytest-cov ; extra == 'test'
